geobeam/__init__.py
geobeam/fn.py
geobeam/io.py
geobeam/util.py
geobeam/examples/__init__.py
geobeam/examples/bigquery_reproject.py
geobeam/examples/crop_geotiff.py
geobeam/examples/geodatabase_frd.py
geobeam/examples/geojson_stormwater.py
geobeam/examples/geotiff_dem.py
geobeam/examples/geotiff_sentinel.py
geobeam/examples/geotiff_soilgrid.py
geobeam/examples/rasterblocksource.py
geobeam/examples/shapefile_nfhl.py
geobeam/examples/shapefile_parcel.py
geobeam/examples/shapefile_parcel_elt.py
geobeam/examples/streaming_pubsub.py
geobeam-1.1.2.dist-info/LICENSE
geobeam-1.1.2.dist-info/METADATA
geobeam-1.1.2.dist-info/WHEEL
geobeam-1.1.2.dist-info/top_level.txt
geobeam-1.1.2.dist-info/RECORD
