Metadata-Version: 2.1
Name: geobeam
Version: 1.1.2
Summary: geobeam adds GIS capabilities to your Apache Beam pipelines
Home-page: UNKNOWN
Author: Travis Webb
Author-email: traviswebb@google.com
License: UNKNOWN
Keywords: beam dataflow gdal gis
Platform: UNKNOWN
Classifier: Development Status :: 4 - Beta
Classifier: License :: OSI Approved :: Apache Software License
Classifier: Programming Language :: Python :: 3
Classifier: Topic :: Scientific/Engineering :: GIS
Classifier: Intended Audience :: Science/Research
Classifier: Intended Audience :: Developers
Requires-Python: >=3.8
Requires-Dist: apache-beam[gcp] (==2.46.0)
Requires-Dist: fiona (==1.9.3)
Requires-Dist: shapely (==1.8.5)
Requires-Dist: rasterio (==1.3.6)
Requires-Dist: google-cloud-storage (==2.5.0)
Requires-Dist: esridump (==1.11.0)
